phoenix/__init__.py
phoenix/__version__.py
phoenix/client.py
phoenix_rec-1.0.3.dist-info/LICENSE
phoenix_rec-1.0.3.dist-info/METADATA
phoenix_rec-1.0.3.dist-info/WHEEL
phoenix_rec-1.0.3.dist-info/top_level.txt
phoenix_rec-1.0.3.dist-info/RECORD
